moranpycess/CustomExceptions.py
moranpycess/Individual.py
moranpycess/MoranProcess.py
moranpycess/MoranProcess2D.py
moranpycess/MoranProcess3D.py
moranpycess/__init__.py
moranpycess-1.1.0.dist-info/LICENSE
moranpycess-1.1.0.dist-info/METADATA
moranpycess-1.1.0.dist-info/WHEEL
moranpycess-1.1.0.dist-info/top_level.txt
moranpycess-1.1.0.dist-info/RECORD
