Metadata-Version: 2.1
Name: moranpycess
Version: 1.1.0
Summary: Python framework for Moran Processes driven by game theory
Author-email: Maciek Bak <wsciekly.maciek@gmail.com>
License: MIT
Project-URL: homepage, https://angrymaciek.github.io/angry-moran-simulator/_build/html/index.html
Project-URL: repository, https://github.com/AngryMaciek/angry-moran-simulator
Classifier: License :: OSI Approved :: MIT License
Classifier: Operating System :: OS Independent
Classifier: Programming Language :: Python :: 3.7
Classifier: Topic :: Software Development :: Libraries :: Python Modules
Requires-Python: >=3.9
License-File: LICENSE
Requires-Dist: matplotlib (>=3.3.4)
Requires-Dist: numpy (>=1.19.5)
Requires-Dist: pandas (>=1.1.5)
Requires-Dist: scipy (>=1.5.3)
Requires-Dist: seaborn (>=0.11.2)
